{
    "$schema": "http://json-schema.org/draft-04/schema#",
    "title": "Contact telephone",
    "description": "A domain schema that describes the telephone contact information.",
    "type": "object",
    "additionalProperties": false,
    "properties": {
        "countryCallCode": {
            "type": "string",
            "description": "Country call code."
        },
        "areaCode": {
            "type": "string",
            "description": "Area code."
        },
        "number": {
            "type": "string",
            "description": "Phone number."
        },
        "extensionNumber": {
            "type": "string",
            "description": "Extension number."
        }
    }
}