{
    "$schema": "http://json-schema.org/draft-04/schema#",
    "type": "object",
    "properties": {
        "criteria": {
            "type": "object",
            "additionalProperties": false,
            "properties": {
                "enableGrouping": {
                    "type": "boolean"
                },
                "documentNo": {
                    "type": "string"
                },
                "mainContractNo": {
                    "type": "string"
                },
                "contractNo": {
                    "type": "string"
                },
                "actId": {
                    "type": "integer"
                },
                "actNo": {
                    "type": "string"
                },
                "bankStatementItemId": {
                    "type": "integer"
                },
                "transactionTypeIds": {
                    "type": "array",
                    "items": {
                        "$ref": "component:TransactionTypeIdComponent"
                    }
                }
            }
        }
    }
}