{
    "$schema": "http://json-schema.org/draft-04/schema#",
    "additionalProperties": false,
    "properties": {
        "bankStatementItemId": {
            "type": "integer"
        },
        "bankStatementItemAmount": {
            "type": "number"
        },
        "bankStatementItemDirection": {
            "type": "integer"
        },
        "allocationDocumentNo": {
            "type": "string"
        },
        "allocationPayAmountSum": {
            "type": "number"
        }
    }
}