{
    "$schema": "http://json-schema.org/draft-04/schema#",
    "title": "Life Insurance",
    "description": "Data schema describing Policy Term",
    "type": "object",
    "additionalProperties": false,
    "aiDataEnrichment": [
        {
            "name": "setPolicyTermsEnrichment"
        }
    ],
    "aiValidation": {
        "rule": "validationPolicyTerms"
    },
    "properties": {
        "startDate": {
            "type": "string",
            "aiFormat": "date",
            "aiTitle": "startDate"
        },
        "endDate": {
            "type": "string",
            "aiFormat": "date",
            "aiTitle": "endDate"
        },
        "effectiveDate": {
            "type": "string",
            "aiFormat": "date",
            "aiTitle": "effectiveDate"
        },
        "paymentPeriodStartDate": {
            "type": "string",
            "aiFormat": "date",
            "aiTitle": "paymentPeriodStartDate"
        },
        "paymentPeriodEndDate": {
            "type": "string",
            "aiFormat": "date",
            "aiTitle": "paymentPeriodEndDate"
        },
        "accumulationPeriodStartDate": {
            "type": "string",
            "aiFormat": "date",
            "aiTitle": "accumulationPeriodStartDate"
        },
        "accumulationPeriodEndDate": {
            "type": "string",
            "aiFormat": "date",
            "aiTitle": "accumulationPeriodEndDate"
        },
        "payOutStartDate": {
            "type": "string",
            "aiFormat": "date",
            "aiTitle": "payOutStartDate"
        },
        "payOutEndDate": {
            "type": "string",
            "aiFormat": "date",
            "aiTitle": "payOutEndDate"
        },
        "paymentPeriodString": {
            "type": "string",
            "aiTitle": "paymentPeriodString"
        },
        "manualCorrection": {
            "type": "boolean",
            "aiTitle": "manualCorrection"
        },
        "paymentPeriodLastDate": {
            "type": "string",
            "aiFormat": "date",
            "aiTitle": "paymentPeriodLastDate"
        }
    }
}