{
    "$schema": "http://json-schema.org/draft-04/schema#",
    "type":"object",
    "additionalProperties": false,
    "properties": {
        "claimNumber": {
            "type": "string"
        },
        "contractNumber": {
            "type": "string"
        },
        "riskCode": {
            "type": "string"
        }, 
        "riskDescription": {
            "type": "string"
        },
        "contractCurrency": {
            "type": "string"
        },
        "shouldUseNetting": {
            "type": "boolean"
        }, 
        "nonAcceptance": {
            "type": "boolean"
        },
        "numberOfNonAcceptancePayment": {
            "type": "string"
        },
        "fixedExchangeRate": {
            "type": "number"
        },
        "useFixedExchangeRate": {
            "type": "boolean"
        },
        "holderPartyCode": {
            "type": "string"
        },
        "amountInContractCurrency": {
            "type": "number"
        },
        "amountInRub": {
            "type": "number"
        }
    }
}
