{
    "entityType": "Contract",
    "condition": {
        "events": [
            "Created",
            "StatusChanged"
        ],
        "configuration": {
            "names": [
                "AccidentLifeInsurancePolicy"
            ]
        },
        "documentStates": [
            "Completed"
        ]
    },
    "sinks": [
        {
            "name": "GetRisks",
            "fetch": {
                "configuration": {
                    "name": "RiskContractDataSource"
                }
            }
        },
        {
            "name": "CreateEndowment",
            "documentRelation": {
                "relation": {
                    "relationName": "CreateEndowment",
                    "configurationName": "AccidentLifeInsurancePolicy",
                    "configurationVersion": "1"
                }
            }
        }
    ],
    "version": "1"
}