{
    "$schema": "http://json-schema.org/draft-04/schema#",
    "title": "Collective life insurance",
    "description": "Data schema describing issue form for collective policies",
    "type": "object",
    "aiTitle": "issueForm",
    "additionalProperties": false,
    "aiDataEnrichment": [
        {
            "name": "setIssueFormEnrichment",
            "dataSource": "IssueFormDataSource"
        }
    ],
    "properties": {
        "code": {
            "type": "object",
            "aiTitle": "issueForm",
            "additionalProperties": false,
            "properties": {
                "issueFormCode": {
                    "type": "string",
                    "aiTitle": "issueFormCode"
                },
                "issueFormDescription": {
                    "type": "string",
                    "aiTitle": "issueFormDescription"
                }
            }
        }
    }
}