{
    "$schema": "http://json-schema.org/draft-04/schema#",
    "description": "Business activity data source input schema",
    "type": "object",
    "properties": {
        "criteria": {
            "type": "object",
            "additionalProperties": false,
            "properties": {
                "subgroupCodeLevel1": {
                    "type": "string"
                },
                "subgroupCodeLevel2": {
                    "type": "string"
                },
                "subgroupCodeLevel3": {
                    "type": "string"
                },
                "description": {
                    "type": "string"
                },
                "group": {
                    "type": "string"
                },
                "ruleCode": {
                    "type": "string"
                },
                "note": {
                    "type": "string"
                }
            }
        }
    }
}