{
    "$schema": "http://json-schema.org/draft-04/schema#",
    "type": "object",
    "additionalProperties": false,
    "properties": {
        "productConfNumber": {
            "type": "string"
        },
        "universalMasterEntityCode": {
            "type": "string"
        },
        "contractNumber": {
            "type": "string"
        },
        "contractCodeName": {
            "type": "string"
        },
        "productCode": {
            "type": "string"
        },
        "ruleNum": {
            "type": "number",
            "aiType": "int"
        },
        "policyIssueDateStart": {
            "type": "string",
            "aiFormat": "date"
        },
        "policyIssueDateEnd": {
            "type": "string",
            "aiFormat": "date"
        },
        "insuranceTermFrom": {
            "type": "integer"
        },
        "insuranceTermTo": {
            "type": "integer"
        },
        "partnerCode": {
            "type": "string"
        },
        "partnerBusinessCode": {
            "type": "string"
        },
        "agentAgreementId": {
            "type": "string"
        },
        "agentAgreementNumber": {
            "type": "string"
        },
        "agentAgreementExternalNumber": {
            "type": "string"
        },
        "agentAgreementManualNumber": {
            "type": "string"
        },
        "agentAgreementCommRate": {
            "type": "number"
        },
        "currencyNumericCode": {
            "type": "string"
        },
        "paymentFrequencyCode": {
            "type": "string"
        },
        "guaranteedIncomeCode": {
            "type": "string"
        },
        "bipStrategyCode": {
            "type": "string"
        },
        "bipStrategyDescription": {
            "type": "string"
        },
        "rorIssueDateFrom": {
            "type": "string",
            "format": "date",
            "aiFormat": "date"
        },
        "rorIssueDateTo": {
            "type": "string",
            "format": "date",
            "aiFormat": "date"
        },
        "rorStrategyCode": {
            "type": "string"
        },
        "rorInsuranceTerms": {
            "type": "string"
        },
        "rorCurrencyCode": {
            "type": "string"
        },
        "rorGuaranteedIncome": {
            "type": "string"
        },
        "scIssueDateFrom": {
            "type": "string",
            "format": "date",
            "aiFormat": "date"
        },
        "scIssueDateTo": {
            "type": "string",
            "format": "date",
            "aiFormat": "date"
        },
        "scCurrencyCode": {
            "type": "string"
        },
        "segment": {
            "type": "string"
        },
        "isin": {
            "type": "string"
        },
        "rko": {
            "type": "number"
        },
        "motivationFromMargin": {
            "type": "number"
        },
        "motivationFromProductEconomic": {
            "type": "number"
        },
        "skMargin": {
            "type": "number"
        },
        "fundingRateSwaps": {
            "type": "number"
        },
        "laps": {
            "type": "number"
        },
        "hedge": {
            "type": "number"
        },
        "clientID": {
            "type": "number"
        },
        "shareRF": {
            "type": "number"
        },
        "shareGF": {
            "type": "number"
        },
        "rvd": {
            "type": "number"
        },
        "fundingVersionSubFundID": {
            "type": "integer"
        },
        "memorandumPkDate": {
            "type": "string",
            "format": "date",
            "aiFormat": "date"
        },
        "pkNumber": {
            "type": "integer"
        },
        "analyticalAdjustment": {
            "type": "number"
        },
        "expectedReturnPercentAK": {
            "type": "number"
        },
        "insurance": {
            "type": "number"
        },
        "riskTransferProduct": {
            "type": "string"
        },
        "comments": {
            "type": "string"
        },
        "isManualCorrection": {
            "type": "boolean"
        },
        "rorRateOfReturn": {
            "type": "number"
        },
        "scOptionPrice": {
            "type": "number"
        },
        "scFixRate": {
            "type": "number"
        },
        "scParticipationCoeff": {
            "type": "number"
        }
    }
}